{
    "UMass-AR2": {
        "target_end_date": [
            "2023-10-21",
            "2023-10-28",
            "2023-11-04",
            "2023-11-11"
        ],
        "q0.025": [
            0.0,
            0.0,
            0.0,
            0.0
        ],
        "q0.25": [
            0.6006069902458678,
            0.0,
            0.0,
            0.0
        ],
        "q0.5": [
            9.374413742074664,
            10.439794903700864,
            14.824385078515627,
            19.664124271243917
        ],
        "q0.75": [
            19.04512970947888,
            30.08897353138649,
            43.70123920046711,
            56.50274830617832
        ],
        "q0.975": [
            44.58553479248972,
            84.94804842957821,
            130.8218214164902,
            191.21941146975328
        ]
    },
    "UMass-AR6_pooled": {
        "target_end_date": [
            "2023-10-21",
            "2023-10-28",
            "2023-11-04",
            "2023-11-11"
        ],
        "q0.025": [
            0.0,
            0.0,
            0.0,
            0.0
        ],
        "q0.25": [
            5.695212574919195,
            4.200779724236247,
            6.64992773995153,
            8.660633237329993
        ],
        "q0.5": [
            14.454417709496669,
            16.581177596252402,
            24.450109737889623,
            31.606448125573685
        ],
        "q0.75": [
            23.89259915631191,
            33.31382638915011,
            48.36680784176229,
            62.94340127748198
        ],
        "q0.975": [
            47.6705855184662,
            75.55493987814411,
            118.54770465377553,
            167.75324579258896
        ]
    },
    "UMass-AR6_unpooled": {
        "target_end_date": [
            "2023-10-21",
            "2023-10-28",
            "2023-11-04",
            "2023-11-11"
        ],
        "q0.025": [
            0.0,
            0.0,
            0.0,
            0.0
        ],
        "q0.25": [
            5.826661375562906,
            0.6064743694127039,
            4.166056627049473,
            2.615957562520204
        ],
        "q0.5": [
            15.612029441588652,
            12.668184521626758,
            21.890902590873477,
            24.96177149404421
        ],
        "q0.75": [
            25.87630275791159,
            27.88858102935464,
            44.64770408365057,
            53.96447026255392
        ],
        "q0.975": [
            53.52802688876093,
            67.70717931474736,
            105.6344624463071,
            142.70507312510057
        ]
    }
}