{
    "Google_SAI-FluBoostQR": {
        "target_end_date": [
            "2025-05-10",
            "2025-05-17",
            "2025-05-24",
            "2025-05-31"
        ],
        "q0.025": [
            38.57142857142857,
            30.285714285714285,
            23.428571428571427,
            16.142857142857142
        ],
        "q0.25": [
            66.0,
            49.71428571428572,
            34.42857142857143,
            28.571428571428573
        ],
        "q0.5": [
            75.14285714285714,
            60.85714285714285,
            46.0,
            44.42857142857143
        ],
        "q0.75": [
            99.42857142857144,
            92.42857142857144,
            91.28571428571428,
            80.71428571428571
        ],
        "q0.975": [
            137.85714285714286,
            142.71428571428572,
            132.0,
            136.14285714285714
        ]
    },
    "LosAlamos_NAU-CModel_Flu": {
        "target_end_date": [
            "2025-05-10",
            "2025-05-17",
            "2025-05-24",
            "2025-05-31"
        ],
        "q0.025": [
            20.0,
            17.0,
            13.0,
            10.0
        ],
        "q0.25": [
            50.0,
            41.0,
            34.0,
            28.0
        ],
        "q0.5": [
            73.0,
            61.0,
            51.0,
            42.0
        ],
        "q0.75": [
            103.0,
            86.0,
            73.0,
            61.0
        ],
        "q0.975": [
            188.0,
            158.0,
            136.0,
            116.0
        ]
    },
    "fjordhest-ensemble": {
        "target_end_date": [
            "2025-05-10",
            "2025-05-17",
            "2025-05-24",
            "2025-05-31"
        ],
        "q0.025": [
            23.79,
            6.26,
            3.06,
            1.35
        ],
        "q0.25": [
            54.54,
            42.91,
            26.74,
            18.22
        ],
        "q0.5": [
            75.97,
            79.03,
            73.88,
            66.08
        ],
        "q0.75": [
            96.58,
            119.06,
            119.72,
            110.47
        ],
        "q0.975": [
            138.99,
            197.04,
            210.48,
            198.09
        ]
    },
    "CMU-climate_baseline": {
        "target_end_date": [
            "2025-05-03",
            "2025-05-10",
            "2025-05-17",
            "2025-05-24",
            "2025-05-31"
        ],
        "q0.025": [
            2.0,
            2.0,
            2.0,
            2.0,
            2.0
        ],
        "q0.25": [
            18.958333333333336,
            17.833333333333336,
            15.499999999999996,
            9.708333333333336,
            6.0
        ],
        "q0.5": [
            30.0,
            28.75,
            28.750000000000004,
            29.75,
            32.00000000000001
        ],
        "q0.75": [
            53.25000000000005,
            57.20833333333336,
            55.70833333333336,
            54.20833333333336,
            52.75000000000005
        ],
        "q0.975": [
            313.08749999999986,
            308.66666666666606,
            309.1041666666666,
            309.729166666666,
            310.35416666666544
        ]
    },
    "UMass-trends_ensemble": {
        "target_end_date": [
            "2025-05-10",
            "2025-05-17",
            "2025-05-24",
            "2025-05-31"
        ],
        "q0.025": [
            38.0,
            9.5,
            1.0,
            0.0
        ],
        "q0.25": [
            51.0,
            35.5,
            24.5,
            14.5
        ],
        "q0.5": [
            87.5,
            80.5,
            72.5,
            65.5
        ],
        "q0.75": [
            129.5,
            121.5,
            118.5,
            114.5
        ],
        "q0.975": [
            168.0,
            216.0,
            234.5,
            245.5
        ]
    },
    "UVAFluX-OptimWISE": {
        "target_end_date": [
            "2025-05-10",
            "2025-05-17",
            "2025-05-24",
            "2025-05-31"
        ],
        "q0.025": [
            42.0,
            44.0,
            33.0,
            28.0
        ],
        "q0.25": [
            62.0,
            66.0,
            52.0,
            48.0
        ],
        "q0.5": [
            90.0,
            88.0,
            72.0,
            62.0
        ],
        "q0.75": [
            119.0,
            111.0,
            97.0,
            76.0
        ],
        "q0.975": [
            180.0,
            160.0,
            149.0,
            108.0
        ]
    },
    "CMU-TimeSeries": {
        "target_end_date": [
            "2025-05-03",
            "2025-05-10",
            "2025-05-17",
            "2025-05-24",
            "2025-05-31"
        ],
        "q0.025": [
            56.25796464235884,
            22.7908812052215,
            10.531389959083224,
            7.599011618125933,
            6.550639344351838
        ],
        "q0.25": [
            100.4266645784902,
            61.010668645657205,
            34.6901707511941,
            21.58685457298913,
            19.086392549493983
        ],
        "q0.5": [
            117.4396295808709,
            75.7521140763821,
            49.89056585086733,
            30.94425618664089,
            32.0215246935238
        ],
        "q0.75": [
            131.32055560166984,
            90.22217570769448,
            70.28790852864452,
            57.22551131955792,
            61.19353699763009
        ],
        "q0.975": [
            184.6118360104409,
            180.4125316816568,
            192.23657238332743,
            196.44326879793837,
            200.2787944213076
        ]
    },
    "FluSight-lop_norm": {
        "target_end_date": [
            "2025-05-10",
            "2025-05-17",
            "2025-05-24",
            "2025-05-31"
        ],
        "q0.025": [
            0,
            0,
            0,
            0
        ],
        "q0.25": [
            61,
            47,
            35,
            28
        ],
        "q0.5": [
            89,
            77,
            66,
            59
        ],
        "q0.75": [
            118,
            114,
            105,
            97
        ],
        "q0.975": [
            222,
            241,
            254,
            265
        ]
    },
    "ISU_NiemiLab-GPE": {
        "target_end_date": [
            "2025-05-10",
            "2025-05-17",
            "2025-05-24",
            "2025-05-31"
        ],
        "q0.025": [
            17.4294224295067,
            7.29249307563408,
            5.53319305145465,
            2.06104910040049
        ],
        "q0.25": [
            36.1967841135272,
            22.3037037540473,
            21.1611159163113,
            15.7780598819748
        ],
        "q0.5": [
            101.891149786489,
            89.9247031293448,
            86.4276068162691,
            78.4622688398926
        ],
        "q0.75": [
            119.042822808135,
            114.636454376909,
            119.00246550231,
            116.10071576175
        ],
        "q0.975": [
            184.049427551349,
            172.593957333685,
            174.502751067544,
            175.273542660115
        ]
    },
    "UGuelph-CompositeCurve": {
        "target_end_date": [
            "2025-05-03",
            "2025-05-10",
            "2025-05-17",
            "2025-05-24",
            "2025-05-31"
        ],
        "q0.025": [
            102.0,
            75.0,
            64.0,
            53.0,
            50.0
        ],
        "q0.25": [
            102.0,
            86.0,
            72.0,
            61.0,
            56.0
        ],
        "q0.5": [
            102.0,
            91.0,
            78.0,
            67.0,
            62.0
        ],
        "q0.75": [
            102.0,
            96.0,
            82.0,
            74.0,
            66.0
        ],
        "q0.975": [
            102.0,
            106.0,
            101.0,
            92.0,
            99.0
        ]
    },
    "FluSight-trained_mean": {
        "target_end_date": [
            "2025-05-10",
            "2025-05-17",
            "2025-05-24",
            "2025-05-31"
        ],
        "q0.025": [
            28.83217030579648,
            14.472425428540705,
            7.999667994205916,
            5.2355502218232255
        ],
        "q0.25": [
            45.62968475160845,
            30.45062298664228,
            22.62655038643188,
            18.491895876791464
        ],
        "q0.5": [
            91.10910505732,
            78.07872450346512,
            68.71383214801824,
            62.58921489537944
        ],
        "q0.75": [
            110.29327933868186,
            107.53187136112923,
            106.6212991588908,
            104.95765914605478
        ],
        "q0.975": [
            174.64497831242525,
            195.2099352832247,
            219.405482005248,
            236.59215702631647
        ]
    },
    "PSI-PROF": {
        "target_end_date": [
            "2025-05-10",
            "2025-05-17",
            "2025-05-24",
            "2025-05-31"
        ],
        "q0.025": [
            0.0,
            0.0,
            0.0,
            0.0
        ],
        "q0.25": [
            12.2,
            7.4,
            7.6,
            7.8
        ],
        "q0.5": [
            97.2,
            94.35,
            90.01,
            87.72
        ],
        "q0.75": [
            112.2,
            118.4,
            123.11,
            128.8
        ],
        "q0.975": [
            183.3,
            174.4,
            170.61,
            181.34
        ]
    },
    "UMass-AR2": {
        "target_end_date": [
            "2025-05-10",
            "2025-05-17",
            "2025-05-24",
            "2025-05-31"
        ],
        "q0.025": [
            45.36171400246202,
            30.05197023273432,
            24.243679901694907,
            17.941062770568927
        ],
        "q0.25": [
            79.1477265204984,
            71.58034885532872,
            66.78859266616374,
            63.57243067532308
        ],
        "q0.5": [
            100.47139928818146,
            98.71281035908584,
            99.91494393197874,
            100.53145863919966
        ],
        "q0.75": [
            125.05574230674172,
            134.5250620113382,
            143.7954492459063,
            150.63623439527944
        ],
        "q0.975": [
            186.4602727176359,
            225.8046180339444,
            257.24954768352904,
            281.6972747012974
        ]
    },
    "UGA_CEID-Walk": {
        "target_end_date": [
            "2025-05-10",
            "2025-05-17",
            "2025-05-24",
            "2025-05-31"
        ],
        "q0.025": [
            0.0,
            0.0,
            0.0,
            0.0
        ],
        "q0.25": [
            52.659,
            48.438,
            33.066,
            35.315
        ],
        "q0.5": [
            103.085,
            102.396,
            110.122,
            109.88
        ],
        "q0.75": [
            147.021,
            172.939,
            206.384,
            203.783
        ],
        "q0.975": [
            213.571,
            293.144,
            342.278,
            385.599
        ]
    },
    "FluSight-trained_med": {
        "target_end_date": [
            "2025-05-10",
            "2025-05-17",
            "2025-05-24",
            "2025-05-31"
        ],
        "q0.025": [
            8.0,
            5.0,
            4.0,
            3.5
        ],
        "q0.25": [
            49.5,
            37.84508537559705,
            27.326427286494567,
            21.04319627474699
        ],
        "q0.5": [
            83.628197755,
            65.5,
            56.0,
            48.0
        ],
        "q0.75": [
            114.1,
            119.75,
            122.055,
            117.4
        ],
        "q0.975": [
            187.0,
            186.1182861916637,
            186.9066343989692,
            195.52439721065377
        ]
    },
    "PSI-PROF_beta": {
        "target_end_date": [
            "2025-05-10",
            "2025-05-17",
            "2025-05-24",
            "2025-05-31"
        ],
        "q0.025": [
            0.0,
            0.0,
            0.0,
            1.0
        ],
        "q0.25": [
            0.0,
            0.0,
            4.25,
            9.0
        ],
        "q0.5": [
            95.75,
            93.03,
            93.25,
            93.0
        ],
        "q0.75": [
            111.75,
            119.5,
            128.25,
            137.0
        ],
        "q0.975": [
            165.75,
            170.51,
            177.37,
            190.77
        ]
    },
    "FluSight-ensemble": {
        "target_end_date": [
            "2025-05-10",
            "2025-05-17",
            "2025-05-24",
            "2025-05-31"
        ],
        "q0.025": [
            36.0,
            23.0,
            13.0,
            7.0
        ],
        "q0.25": [
            63.0,
            49.0,
            35.0,
            28.0
        ],
        "q0.5": [
            90.0,
            80.0,
            69.0,
            58.0
        ],
        "q0.75": [
            115.0,
            119.0,
            107.0,
            93.0
        ],
        "q0.975": [
            185.0,
            180.0,
            180.0,
            183.0
        ]
    },
    "UGA_flucast-Scenariocast": {
        "target_end_date": [
            "2025-05-10",
            "2025-05-17",
            "2025-05-24",
            "2025-05-31"
        ],
        "q0.025": [
            10,
            6,
            3,
            1
        ],
        "q0.25": [
            37,
            22,
            15,
            9
        ],
        "q0.5": [
            59,
            40,
            26,
            19
        ],
        "q0.75": [
            93,
            67,
            45,
            34
        ],
        "q0.975": [
            186,
            138,
            108,
            94
        ]
    },
    "OHT_JHU-nbxd": {
        "target_end_date": [
            "2025-05-10",
            "2025-05-17",
            "2025-05-24",
            "2025-05-31"
        ],
        "q0.025": [
            38.15,
            25.95,
            20.36,
            15.23
        ],
        "q0.25": [
            71.31,
            55.1,
            46.11,
            38.68
        ],
        "q0.5": [
            96.71,
            79.12,
            68.11,
            60.02
        ],
        "q0.75": [
            129.25,
            111.29,
            98.26,
            90.41
        ],
        "q0.975": [
            216.47,
            202.7,
            186.37,
            183.6
        ]
    },
    "UGA_flucast-INFLAenza": {
        "target_end_date": [
            "2025-05-10",
            "2025-05-17",
            "2025-05-24",
            "2025-05-31"
        ],
        "q0.025": [
            40.0,
            27.0,
            19.0,
            15.0
        ],
        "q0.25": [
            71.0,
            59.0,
            51.0,
            44.0
        ],
        "q0.5": [
            95.0,
            89.0,
            83.0,
            76.0
        ],
        "q0.75": [
            128.0,
            134.0,
            132.0,
            129.0
        ],
        "q0.975": [
            220.0,
            278.02499999999964,
            319.02499999999964,
            367.0
        ]
    },
    "UGA_flucast-Copycat": {
        "target_end_date": [
            "2025-05-10",
            "2025-05-17",
            "2025-05-24",
            "2025-05-31"
        ],
        "q0.025": [
            42.0,
            28.0,
            15.0,
            9.0
        ],
        "q0.25": [
            69.0,
            59.0,
            51.0,
            46.0
        ],
        "q0.5": [
            88.0,
            79.0,
            74.0,
            68.0
        ],
        "q0.75": [
            106.0,
            99.0,
            98.0,
            92.0
        ],
        "q0.975": [
            157.0,
            162.0,
            159.0,
            172.0
        ]
    },
    "FluSight-baseline": {
        "target_end_date": [
            "2025-05-03",
            "2025-05-10",
            "2025-05-17",
            "2025-05-24",
            "2025-05-31"
        ],
        "q0.025": [
            102,
            0,
            0,
            0,
            0
        ],
        "q0.25": [
            102,
            90,
            77,
            61,
            48
        ],
        "q0.5": [
            102,
            102,
            102,
            102,
            102
        ],
        "q0.75": [
            102,
            114,
            127,
            143,
            159
        ],
        "q0.975": [
            102,
            231,
            353,
            413,
            453
        ]
    },
    "VTSanghani-PRIME": {
        "target_end_date": [
            "2025-05-10",
            "2025-05-17",
            "2025-05-24",
            "2025-05-31"
        ],
        "q0.025": [
            10,
            7,
            5,
            4
        ],
        "q0.25": [
            19,
            15,
            13,
            11
        ],
        "q0.5": [
            85,
            57,
            50,
            43
        ],
        "q0.75": [
            175,
            145,
            148,
            139
        ],
        "q0.975": [
            453,
            441,
            564,
            782
        ]
    },
    "UVAFluX-Ensemble": {
        "target_end_date": [
            "2025-05-03",
            "2025-05-10",
            "2025-05-17",
            "2025-05-24",
            "2025-05-31"
        ],
        "q0.025": [
            60.0,
            6.0,
            3.0,
            3.0,
            3.0
        ],
        "q0.25": [
            93.0,
            49.0,
            41.0,
            34.0,
            25.0
        ],
        "q0.5": [
            114.0,
            78.0,
            70.0,
            61.0,
            58.0
        ],
        "q0.75": [
            135.0,
            116.0,
            120.0,
            103.0,
            94.0
        ],
        "q0.975": [
            172.0,
            191.0,
            180.0,
            169.0,
            151.0
        ]
    },
    "UMass-flusion": {
        "target_end_date": [
            "2025-05-10",
            "2025-05-17",
            "2025-05-24",
            "2025-05-31"
        ],
        "q0.025": [
            41.6560909704897,
            22.8607278990372,
            14.8143532237338,
            12.1633363962681
        ],
        "q0.25": [
            66.6199305641174,
            49.9781612478967,
            36.3894247505181,
            27.8696181175956
        ],
        "q0.5": [
            81.3579653780729,
            67.4246582039791,
            56.0424501019387,
            48.9144436153597
        ],
        "q0.75": [
            99.5897974058538,
            93.7965190163809,
            86.3381701270377,
            83.24270756479
        ],
        "q0.975": [
            145.012555217991,
            165.557190402453,
            183.66685657147,
            205.187705541962
        ]
    },
    "JHUAPL-DMD": {
        "target_end_date": [
            "2025-05-03",
            "2025-05-10",
            "2025-05-17",
            "2025-05-24",
            "2025-05-31"
        ],
        "q0.025": [
            0.0,
            0.0,
            0.0,
            0.0,
            0.0
        ],
        "q0.25": [
            0.0,
            0.0,
            0.0,
            0.0,
            0.0
        ],
        "q0.5": [
            97.38814346,
            82.25639551,
            46.4235902,
            38.6349865,
            31.34597362
        ],
        "q0.75": [
            220.5008694,
            193.4895945,
            149.9960456,
            155.2876572,
            143.5212901
        ],
        "q0.975": [
            438.6601809,
            539.6442997,
            502.0900517,
            655.4849755,
            936.6211946
        ]
    },
    "CEPH-Rtrend_fluH": {
        "target_end_date": [
            "2025-05-10",
            "2025-05-17",
            "2025-05-24",
            "2025-05-31"
        ],
        "q0.025": [
            60.0,
            26.0,
            11.0,
            4.0
        ],
        "q0.25": [
            88.0,
            58.0,
            37.0,
            23.0
        ],
        "q0.5": [
            108.0,
            88.0,
            68.0,
            51.0
        ],
        "q0.75": [
            132.0,
            130.0,
            121.0,
            106.0
        ],
        "q0.975": [
            186.0,
            256.0,
            305.0,
            308.0
        ]
    },
    "NIH-Flu_ARIMA": {
        "target_end_date": [
            "2025-05-10",
            "2025-05-17",
            "2025-05-24",
            "2025-05-31"
        ],
        "q0.025": [
            46.0,
            30.0,
            21.0,
            17.0
        ],
        "q0.25": [
            58.0,
            43.0,
            37.0,
            34.0
        ],
        "q0.5": [
            63.0,
            50.0,
            47.0,
            45.0
        ],
        "q0.75": [
            68.0,
            59.0,
            61.0,
            62.0
        ],
        "q0.975": [
            93.0,
            96.0,
            116.0,
            130.0
        ]
    }
}