{
    "UMass-AR6_pooled_both": {
        "target_end_date": [
            "2023-12-02",
            "2023-12-09",
            "2023-12-16",
            "2023-12-23"
        ],
        "q0.025": [
            0.0,
            0.0,
            0.0,
            0.0
        ],
        "q0.25": [
            1.1997812872780118,
            1.1373192272611596,
            1.1274016502615156,
            1.2249382155600117
        ],
        "q0.5": [
            2.416934589159411,
            2.8662684081040624,
            3.487902963343663,
            4.0809152717873785
        ],
        "q0.75": [
            3.73379751172189,
            5.107124790381719,
            6.637488014638849,
            8.093439793226556
        ],
        "q0.975": [
            7.032778855390092,
            10.786409480473464,
            14.74136410981266,
            18.60682427159553
        ]
    },
    "UMass-AR6_fourier_pooled_both": {
        "target_end_date": [
            "2023-12-02",
            "2023-12-09",
            "2023-12-16",
            "2023-12-23"
        ],
        "q0.025": [
            0.0,
            0.0,
            0.0,
            0.0
        ],
        "q0.25": [
            1.213991140063609,
            1.1606882257598354,
            1.2139064915323514,
            1.2614465300136122
        ],
        "q0.5": [
            2.421320582650134,
            2.959080217322572,
            3.598003052282689,
            4.240691815733567
        ],
        "q0.75": [
            3.7615067482699223,
            5.172812220518171,
            6.695440907758448,
            8.242091499093112
        ],
        "q0.975": [
            7.078878385269682,
            10.898803399705882,
            14.572493091616789,
            18.695085813058764
        ]
    },
    "UMass-flusion": {
        "target_end_date": [
            "2023-12-02",
            "2023-12-09",
            "2023-12-16",
            "2023-12-23"
        ],
        "q0.025": [
            0.0030684827794019,
            0.0019605447757138,
            0.0069320930018115,
            0.0084243615398686
        ],
        "q0.25": [
            1.03642841828113,
            1.14868039553457,
            1.41502652945603,
            1.57536918163719
        ],
        "q0.5": [
            2.54117356627733,
            3.41215903646233,
            4.57945811516108,
            5.55480371984872
        ],
        "q0.75": [
            4.7641067151254,
            7.39670198266078,
            10.8187416387403,
            13.6966873720307
        ],
        "q0.975": [
            11.9256249038361,
            19.2221681526804,
            31.8110020101661,
            43.248778102594
        ]
    },
    "UMass-AR6_fourier_d1_pooled": {
        "target_end_date": [
            "2023-12-02",
            "2023-12-09",
            "2023-12-16",
            "2023-12-23"
        ],
        "q0.025": [
            0.0,
            0.0,
            0.0,
            0.0
        ],
        "q0.25": [
            0.0,
            0.0,
            0.0,
            0.0
        ],
        "q0.5": [
            1.7385261716299754,
            1.7267441586231758,
            1.82838789424625,
            2.008616878672832
        ],
        "q0.75": [
            4.206170430777589,
            6.143811423167708,
            8.443151114312357,
            10.850225457276409
        ],
        "q0.975": [
            12.052811006383571,
            22.565974671033533,
            34.14692137139271,
            52.73033324591179
        ]
    },
    "UMass-AR2": {
        "target_end_date": [
            "2023-12-02",
            "2023-12-09",
            "2023-12-16",
            "2023-12-23"
        ],
        "q0.025": [
            0.0,
            0.0,
            0.0,
            0.0
        ],
        "q0.25": [
            0.2901328134136287,
            0.0528503553806818,
            0.0,
            0.0
        ],
        "q0.5": [
            2.133211002488771,
            2.4153699975774185,
            2.591129759015556,
            2.921611363328996
        ],
        "q0.75": [
            4.538140921312697,
            5.572527443496302,
            6.703273740366491,
            7.297977345047959
        ],
        "q0.975": [
            11.792205793410329,
            15.691950245700816,
            18.59556142896032,
            22.10576261865986
        ]
    },
    "UMass-AR6_pooled_xmas": {
        "target_end_date": [
            "2023-12-02",
            "2023-12-09",
            "2023-12-16",
            "2023-12-23"
        ],
        "q0.025": [
            0.0,
            0.0,
            0.0,
            0.0
        ],
        "q0.25": [
            0.0,
            0.0,
            0.0,
            0.0
        ],
        "q0.5": [
            5.0390631975793685,
            5.446772575300873,
            5.3860477909156135,
            5.886321555776661
        ],
        "q0.75": [
            14.594205628643378,
            30.714314271665472,
            50.02376206865444,
            48.68535757698596
        ],
        "q0.975": [
            55.16821251528905,
            189.6278641016028,
            397.0393498346991,
            530.6129681893877
        ]
    },
    "UMass-AR6_pooled_sigma": {
        "target_end_date": [
            "2023-12-02",
            "2023-12-09",
            "2023-12-16",
            "2023-12-23"
        ],
        "q0.025": [
            0.0,
            0.0,
            0.0,
            0.0
        ],
        "q0.25": [
            1.2664480939698808,
            1.20992576504441,
            1.5242489823032508,
            1.906685089960014
        ],
        "q0.5": [
            2.484292464117049,
            2.700007052818181,
            3.3844848882420715,
            4.105931512702898
        ],
        "q0.75": [
            3.795937227144548,
            4.378840229180045,
            5.812397194112385,
            6.65275307862249
        ],
        "q0.975": [
            6.995551381282926,
            8.634747496565947,
            11.050874075311958,
            13.244380075173542
        ]
    },
    "UMass-AR4_pooled": {
        "target_end_date": [
            "2023-12-02",
            "2023-12-09",
            "2023-12-16",
            "2023-12-23"
        ],
        "q0.025": [
            0.0,
            0.0,
            0.0,
            0.0
        ],
        "q0.25": [
            0.229884332919795,
            0.0,
            0.0,
            0.0
        ],
        "q0.5": [
            2.3185814840790844,
            2.823671708471565,
            3.3903307040728508,
            3.889759131636355
        ],
        "q0.75": [
            5.035602477122949,
            7.940469183332744,
            11.022277237279786,
            14.48162280291374
        ],
        "q0.975": [
            13.24450944342739,
            26.0205184873812,
            40.16697184430829,
            63.62766657072444
        ]
    },
    "UMass-AR6_pooled": {
        "target_end_date": [
            "2023-12-02",
            "2023-12-09",
            "2023-12-16",
            "2023-12-23"
        ],
        "q0.025": [
            0.0,
            0.0,
            0.0,
            0.0
        ],
        "q0.25": [
            0.3175809122179948,
            0.0,
            0.0,
            0.0
        ],
        "q0.5": [
            2.306358244755712,
            2.7928692935565422,
            3.4116996394915757,
            3.950778110314181
        ],
        "q0.75": [
            4.843609782931931,
            7.516895291216816,
            10.3190856280876,
            13.130177092925392
        ],
        "q0.975": [
            12.716637762264243,
            22.602047403042747,
            35.62557443382112,
            47.99014210899108
        ]
    },
    "UMass-AR6_pooled_fourier": {
        "target_end_date": [
            "2023-12-02",
            "2023-12-09",
            "2023-12-16",
            "2023-12-23"
        ],
        "q0.025": [
            0.0,
            0.0,
            0.0,
            0.0
        ],
        "q0.25": [
            0.3093583323928705,
            0.0,
            0.0,
            0.0
        ],
        "q0.5": [
            2.333055683132305,
            2.8670588962261645,
            3.464626963345381,
            4.116784466962894
        ],
        "q0.75": [
            4.867761968684101,
            7.4568980731818755,
            10.201668551374798,
            12.897527709390875
        ],
        "q0.975": [
            12.634062464226984,
            23.719370056441072,
            33.89192980827229,
            45.25600062247827
        ]
    },
    "UMass-AR6_unpooled": {
        "target_end_date": [
            "2023-12-02",
            "2023-12-09",
            "2023-12-16",
            "2023-12-23"
        ],
        "q0.025": [
            0.0,
            0.0,
            0.0,
            0.0
        ],
        "q0.25": [
            0.6067331457809249,
            0.3901278448508261,
            0.6437539851052418,
            0.7757230838385577
        ],
        "q0.5": [
            2.42774619411953,
            2.760953343859685,
            3.3199384970478625,
            3.957976746906499
        ],
        "q0.75": [
            4.678616680119109,
            5.614092339438306,
            7.408449002897999,
            8.57718976195815
        ],
        "q0.975": [
            11.436886686237004,
            14.786486667090236,
            18.70270513031592,
            22.116748665065447
        ]
    }
}